MANIFEST.in
README.rst
setup.cfg
setup.py
data/lite/company.json
docs/HISTORY.rst
docs/TODO.rst
docs/source/cache.rst
docs/source/client.rst
docs/source/index.rst
duedil/__init__.py
duedil/api.py
duedil/cache.py
duedil.egg-info/PKG-INFO
duedil.egg-info/SOURCES.txt
duedil.egg-info/dependency_links.txt
duedil.egg-info/entry_points.txt
duedil.egg-info/not-zip-safe
duedil.egg-info/requires.txt
duedil.egg-info/top_level.txt
duedil/resources/__init__.py
duedil/resources/international/__init__.py
duedil/resources/international/company_report.py
duedil/resources/lite/__init__.py
duedil/resources/lite/company.py
duedil/resources/pro/__init__.py
duedil/resources/pro/company/__init__.py
duedil/resources/pro/company/bank_account.py
duedil/resources/pro/company/company.py
duedil/resources/pro/company/company_keywords.py
duedil/resources/pro/company/director.py
duedil/resources/pro/company/directorship.py
duedil/resources/pro/company/document.py
duedil/resources/pro/company/mortgage.py
duedil/resources/pro/company/parent_companies.py
duedil/resources/pro/company/previous_company_name.py
duedil/resources/pro/company/registered_address.py
duedil/resources/pro/company/secondary_industries.py
duedil/resources/pro/company/service_address.py
duedil/resources/pro/company/shareholder.py
duedil/resources/pro/company/subsidiary_companies.py
duedil/resources/pro/company/accounts/__init__.py
duedil/resources/pro/company/accounts/financial.py
duedil/resources/pro/company/accounts/gaap.py
duedil/resources/pro/company/accounts/ifrs.py
duedil/resources/pro/company/accounts/insurance.py
duedil/resources/pro/company/accounts/statutory.py
duedil/resources/pro/credit/__init__.py
duedil/resources/pro/credit/report.py
duedil/resources/pro/director/__init__.py
duedil/resources/pro/director/companies.py
duedil/resources/pro/director/directorships.py
duedil/resources/pro/director/service_address.py
duedil/search/__init__.py
duedil/search/international/__init__.py
duedil/search/international/company.py
duedil/search/lite/__init__.py
duedil/search/lite/company.py
duedil/search/pro/__init__.py
duedil/search/pro/company.py
duedil/search/pro/director.py