Metadata-Version: 1.1
Name: duedil
Version: 1.0.12
Summary: Duedil API client
Home-page: http://duedilv3.readthedocs.org/en/latest/
Author: Christian Ledermann
Author-email: christian.ledermann@gmail.com
License: Apache License 2.0
Keywords: duedil,api
Platform: UNKNOWN
Classifier: Intended Audience :: Developers
Classifier: License :: OSI Approved :: Apache Software License
Classifier: Programming Language :: Python :: 3
Classifier: Programming Language :: Python :: 2
Classifier: Programming Language :: Python :: 2.7
Classifier: Programming Language :: Python :: 3.3
Classifier: Programming Language :: Python :: 3.4
Classifier: Programming Language :: Python :: 3.5
Classifier: Programming Language :: Python :: 3.6
Classifier: Development Status :: 3 - Alpha
